{
  "_fv": 39,
  "_type": "recipe",
  "definition": {
    "recipeType": "Crafting",
    "xpReward": 0.0,
    "cookingTime": 200,
    "recipeRetstackSize": 1,
    "group": "",
    "recipeShapeless": false,
    "recipeSlots": [
      {
        "value": "Blocks.LOG#1"
      },
      {
        "value": "Blocks.IRON_BLOCK"
      },
      {
        "value": "Blocks.LOG#1"
      },
      {
        "value": "Blocks.STRIPPED_SPRUCE_LOG"
      },
      {
        "value": "Blocks.MOSS_BLOCK"
      },
      {
        "value": "Blocks.STRIPPED_SPRUCE_LOG"
      },
      {
        "value": "Blocks.STRIPPED_SPRUCE_LOG"
      },
      {
        "value": "Blocks.MOSS_BLOCK"
      },
      {
        "value": "Blocks.STRIPPED_SPRUCE_LOG"
      }
    ],
    "recipeReturnStack": {
      "value": "CUSTOM:SlavicTotemUncharged"
    },
    "name": "slavic_totem_craft",
    "namespace": "mod"
  }
}